{
  "run_at": "2026-07-14T11:42:52.056929+00:00",
  "symbols": {
    "AARTIIND": {
      "status": "ok",
      "fundamentals_available": false,
      "analyst_available": false,
      "events_available": false,
      "shareholding_available": false
    },
    "ABBOTINDIA": {
      "status": "ok",
      "fundamentals_available": false,
      "analyst_available": false,
      "events_available": false,
      "shareholding_available": false
    },
    "ACC": {
      "status": "ok",
      "fundamentals_available": false,
      "analyst_available": false,
      "events_available": false,
      "shareholding_available": false
    },
    "ADANIPORTS": {
      "status": "ok",
      "fundamentals_available": false,
      "analyst_available": false,
      "events_available": false,
      "shareholding_available": false
    },
    "ADANIPOWER": {
      "status": "ok",
      "fundamentals_available": false,
      "analyst_available": false,
      "events_available": false,
      "shareholding_available": false
    },
    "AMARAJABAT": {
      "status": "skipped",
      "reason": "no symboltoken found"
    },
    "AMBER": {
      "status": "ok",
      "fundamentals_available": false,
      "analyst_available": false,
      "events_available": false,
      "shareholding_available": false
    },
    "AMBUJACEM": {
      "status": "ok",
      "fundamentals_available": false,
      "analyst_available": false,
      "events_available": false,
      "shareholding_available": false
    },
    "APOLLOHOSP": {
      "status": "ok",
      "fundamentals_available": false,
      "analyst_available": false,
      "events_available": false,
      "shareholding_available": false
    },
    "ASHOKA": {
      "status": "ok",
      "fundamentals_available": false,
      "analyst_available": false,
      "events_available": false,
      "shareholding_available": false
    },
    "ASHOKLEY": {
      "status": "ok",
      "fundamentals_available": false,
      "analyst_available": false,
      "events_available": false,
      "shareholding_available": false
    },
    "ASIANPAINT": {
      "status": "ok",
      "fundamentals_available": false,
      "analyst_available": false,
      "events_available": false,
      "shareholding_available": false
    },
    "ASTRAMICRO": {
      "status": "ok",
      "fundamentals_available": false,
      "analyst_available": false,
      "events_available": false,
      "shareholding_available": false
    },
    "AUBANK": {
      "status": "ok",
      "fundamentals_available": false,
      "analyst_available": false,
      "events_available": false,
      "shareholding_available": false
    },
    "AUROPHARMA": {
      "status": "ok",
      "fundamentals_available": false,
      "analyst_available": false,
      "events_available": false,
      "shareholding_available": false
    },
    "AXISBANK": {
      "status": "ok",
      "fundamentals_available": false,
      "analyst_available": false,
      "events_available": false,
      "shareholding_available": false
    },
    "BAJAJ-AUTO": {
      "status": "ok",
      "fundamentals_available": false,
      "analyst_available": false,
      "events_available": false,
      "shareholding_available": false
    },
    "BAJAJFINSV": {
      "status": "ok",
      "fundamentals_available": false,
      "analyst_available": false,
      "events_available": false,
      "shareholding_available": false
    },
    "BAJAJHFL": {
      "status": "ok",
      "fundamentals_available": false,
      "analyst_available": false,
      "events_available": false,
      "shareholding_available": false
    },
    "BAJFINANCE": {
      "status": "ok",
      "fundamentals_available": false,
      "analyst_available": false,
      "events_available": false,
      "shareholding_available": false
    },
    "BALKRISIND": {
      "status": "ok",
      "fundamentals_available": false,
      "analyst_available": false,
      "events_available": false,
      "shareholding_available": false
    },
    "BANKBARODA": {
      "status": "ok",
      "fundamentals_available": false,
      "analyst_available": false,
      "events_available": false,
      "shareholding_available": false
    },
    "BDL": {
      "status": "ok",
      "fundamentals_available": false,
      "analyst_available": false,
      "events_available": false,
      "shareholding_available": false
    },
    "BEL": {
      "status": "ok",
      "fundamentals_available": false,
      "analyst_available": false,
      "events_available": false,
      "shareholding_available": false
    },
    "BEML": {
      "status": "ok",
      "fundamentals_available": false,
      "analyst_available": false,
      "events_available": false,
      "shareholding_available": false
    },
    "BHARTIARTL": {
      "status": "ok",
      "fundamentals_available": false,
      "analyst_available": false,
      "events_available": false,
      "shareholding_available": false
    },
    "BLUEDART": {
      "status": "ok",
      "fundamentals_available": false,
      "analyst_available": false,
      "events_available": false,
      "shareholding_available": false
    },
    "BOSCHLTD": {
      "status": "ok",
      "fundamentals_available": false,
      "analyst_available": false,
      "events_available": false,
      "shareholding_available": false
    },
    "BPCL": {
      "status": "ok",
      "fundamentals_available": false,
      "analyst_available": false,
      "events_available": false,
      "shareholding_available": false
    },
    "BRIGADE": {
      "status": "ok",
      "fundamentals_available": false,
      "analyst_available": false,
      "events_available": false,
      "shareholding_available": false
    },
    "BRITANNIA": {
      "status": "ok",
      "fundamentals_available": false,
      "analyst_available": false,
      "events_available": false,
      "shareholding_available": false
    },
    "CANBK": {
      "status": "ok",
      "fundamentals_available": false,
      "analyst_available": false,
      "events_available": false,
      "shareholding_available": false
    },
    "CESC": {
      "status": "ok",
      "fundamentals_available": false,
      "analyst_available": false,
      "events_available": false,
      "shareholding_available": false
    },
    "CHAMBLFERT": {
      "status": "ok",
      "fundamentals_available": false,
      "analyst_available": false,
      "events_available": false,
      "shareholding_available": false
    },
    "CHOLAFIN": {
      "status": "ok",
      "fundamentals_available": false,
      "analyst_available": false,
      "events_available": false,
      "shareholding_available": false
    },
    "CIPLA": {
      "status": "ok",
      "fundamentals_available": false,
      "analyst_available": false,
      "events_available": false,
      "shareholding_available": false
    },
    "COCHINSHIP": {
      "status": "ok",
      "fundamentals_available": false,
      "analyst_available": false,
      "events_available": false,
      "shareholding_available": false
    },
    "COFORGE": {
      "status": "ok",
      "fundamentals_available": false,
      "analyst_available": false,
      "events_available": false,
      "shareholding_available": false
    },
    "COLPAL": {
      "status": "ok",
      "fundamentals_available": false,
      "analyst_available": false,
      "events_available": false,
      "shareholding_available": false
    },
    "CONCOR": {
      "status": "ok",
      "fundamentals_available": false,
      "analyst_available": false,
      "events_available": false,
      "shareholding_available": false
    },
    "COROMANDEL": {
      "status": "skipped",
      "reason": "ohlcv fetch failed"
    },
    "DABUR": {
      "status": "skipped",
      "reason": "ohlcv fetch failed"
    },
    "DALBHARAT": {
      "status": "skipped",
      "reason": "ohlcv fetch failed"
    },
    "DEEPAKNTR": {
      "status": "skipped",
      "reason": "ohlcv fetch failed"
    },
    "DELHIVERY": {
      "status": "skipped",
      "reason": "ohlcv fetch failed"
    },
    "DIVISLAB": {
      "status": "skipped",
      "reason": "ohlcv fetch failed"
    },
    "DIXON": {
      "status": "skipped",
      "reason": "ohlcv fetch failed"
    },
    "DLF": {
      "status": "skipped",
      "reason": "ohlcv fetch failed"
    },
    "DRREDDY": {
      "status": "skipped",
      "reason": "ohlcv fetch failed"
    },
    "EICHERMOT": {
      "status": "skipped",
      "reason": "ohlcv fetch failed"
    },
    "EXIDEIND": {
      "status": "skipped",
      "reason": "ohlcv fetch failed"
    },
    "FACT": {
      "status": "skipped",
      "reason": "ohlcv fetch failed"
    },
    "FEDERALBNK": {
      "status": "skipped",
      "reason": "ohlcv fetch failed"
    },
    "FORTIS": {
      "status": "skipped",
      "reason": "ohlcv fetch failed"
    },
    "GAIL": {
      "status": "skipped",
      "reason": "ohlcv fetch failed"
    },
    "GNFC": {
      "status": "skipped",
      "reason": "ohlcv fetch failed"
    },
    "GODREJCP": {
      "status": "skipped",
      "reason": "ohlcv fetch failed"
    },
    "GODREJPROP": {
      "status": "skipped",
      "reason": "ohlcv fetch failed"
    },
    "GRSE": {
      "status": "skipped",
      "reason": "ohlcv fetch failed"
    },
    "HAL": {
      "status": "skipped",
      "reason": "ohlcv fetch failed"
    },
    "HCLTECH": {
      "status": "skipped",
      "reason": "ohlcv fetch failed"
    },
    "HDFCBANK": {
      "status": "skipped",
      "reason": "ohlcv fetch failed"
    },
    "HEROMOTOCO": {
      "status": "skipped",
      "reason": "ohlcv fetch failed"
    },
    "HFCL": {
      "status": "skipped",
      "reason": "ohlcv fetch failed"
    },
    "HGINFRA": {
      "status": "skipped",
      "reason": "ohlcv fetch failed"
    },
    "HINDALCO": {
      "status": "skipped",
      "reason": "ohlcv fetch failed"
    },
    "HINDPETRO": {
      "status": "skipped",
      "reason": "ohlcv fetch failed"
    },
    "HINDUNILVR": {
      "status": "skipped",
      "reason": "ohlcv fetch failed"
    },
    "ICICIBANK": {
      "status": "skipped",
      "reason": "ohlcv fetch failed"
    },
    "IDEA": {
      "status": "skipped",
      "reason": "ohlcv fetch failed"
    },
    "IDFCFIRSTB": {
      "status": "skipped",
      "reason": "ohlcv fetch failed"
    },
    "IGL": {
      "status": "skipped",
      "reason": "ohlcv fetch failed"
    },
    "INDIGO": {
      "status": "skipped",
      "reason": "ohlcv fetch failed"
    },
    "INDUSINDBK": {
      "status": "skipped",
      "reason": "ohlcv fetch failed"
    },
    "INDUSTOWER": {
      "status": "skipped",
      "reason": "ohlcv fetch failed"
    },
    "INFY": {
      "status": "skipped",
      "reason": "ohlcv fetch failed"
    },
    "IOC": {
      "status": "skipped",
      "reason": "ohlcv fetch failed"
    },
    "IRB": {
      "status": "skipped",
      "reason": "ohlcv fetch failed"
    },
    "IRCON": {
      "status": "skipped",
      "reason": "ohlcv fetch failed"
    },
    "IRCTC": {
      "status": "skipped",
      "reason": "ohlcv fetch failed"
    },
    "IRFC": {
      "status": "skipped",
      "reason": "ohlcv fetch failed"
    },
    "ITC": {
      "status": "skipped",
      "reason": "ohlcv fetch failed"
    },
    "JINDALSTEL": {
      "status": "skipped",
      "reason": "ohlcv fetch failed"
    },
    "JIOFIN": {
      "status": "skipped",
      "reason": "ohlcv fetch failed"
    },
    "JKCEMENT": {
      "status": "skipped",
      "reason": "ohlcv fetch failed"
    },
    "JSWENERGY": {
      "status": "skipped",
      "reason": "ohlcv fetch failed"
    },
    "JSWINFRA": {
      "status": "skipped",
      "reason": "ohlcv fetch failed"
    },
    "JSWSTEEL": {
      "status": "skipped",
      "reason": "ohlcv fetch failed"
    },
    "JWL": {
      "status": "skipped",
      "reason": "ohlcv fetch failed"
    },
    "KALYANKJIL": {
      "status": "skipped",
      "reason": "ohlcv fetch failed"
    },
    "KAYNES": {
      "status": "skipped",
      "reason": "ohlcv fetch failed"
    },
    "KEC": {
      "status": "skipped",
      "reason": "ohlcv fetch failed"
    },
    "KIMS": {
      "status": "skipped",
      "reason": "ohlcv fetch failed"
    },
    "KNRCON": {
      "status": "skipped",
      "reason": "ohlcv fetch failed"
    },
    "KOTAKBANK": {
      "status": "skipped",
      "reason": "ohlcv fetch failed"
    },
    "KPITTECH": {
      "status": "skipped",
      "reason": "ohlcv fetch failed"
    },
    "LICHSGFIN": {
      "status": "skipped",
      "reason": "ohlcv fetch failed"
    },
    "LODHA": {
      "status": "skipped",
      "reason": "ohlcv fetch failed"
    },
    "LT": {
      "status": "skipped",
      "reason": "ohlcv fetch failed"
    },
    "LTIM": {
      "status": "skipped",
      "reason": "no symboltoken found"
    },
    "LTTS": {
      "status": "skipped",
      "reason": "ohlcv fetch failed"
    },
    "LUPIN": {
      "status": "skipped",
      "reason": "ohlcv fetch failed"
    },
    "M&M": {
      "status": "skipped",
      "reason": "ohlcv fetch failed"
    },
    "MANKIND": {
      "status": "skipped",
      "reason": "ohlcv fetch failed"
    },
    "MARICO": {
      "status": "skipped",
      "reason": "ohlcv fetch failed"
    },
    "MARUTI": {
      "status": "skipped",
      "reason": "ohlcv fetch failed"
    },
    "MAXHEALTH": {
      "status": "skipped",
      "reason": "ohlcv fetch failed"
    },
    "MAZDOCK": {
      "status": "skipped",
      "reason": "ohlcv fetch failed"
    },
    "MEDANTA": {
      "status": "skipped",
      "reason": "ohlcv fetch failed"
    },
    "MGL": {
      "status": "skipped",
      "reason": "ohlcv fetch failed"
    },
    "MOTHERSON": {
      "status": "skipped",
      "reason": "ohlcv fetch failed"
    },
    "MPHASIS": {
      "status": "skipped",
      "reason": "ohlcv fetch failed"
    },
    "MUTHOOTFIN": {
      "status": "skipped",
      "reason": "ohlcv fetch failed"
    },
    "NALCO": {
      "status": "skipped",
      "reason": "no symboltoken found"
    },
    "NARAYANA": {
      "status": "skipped",
      "reason": "no symboltoken found"
    },
    "NAVINFLUOR": {
      "status": "skipped",
      "reason": "ohlcv fetch failed"
    },
    "NBCC": {
      "status": "skipped",
      "reason": "ohlcv fetch failed"
    },
    "NCC": {
      "status": "skipped",
      "reason": "ohlcv fetch failed"
    },
    "NESTLEIND": {
      "status": "skipped",
      "reason": "ohlcv fetch failed"
    },
    "NHPC": {
      "status": "skipped",
      "reason": "ohlcv fetch failed"
    },
    "NLCINDIA": {
      "status": "skipped",
      "reason": "ohlcv fetch failed"
    },
    "NMDC": {
      "status": "skipped",
      "reason": "ohlcv fetch failed"
    },
    "NTPC": {
      "status": "skipped",
      "reason": "ohlcv fetch failed"
    },
    "OBEROIRLTY": {
      "status": "skipped",
      "reason": "ohlcv fetch failed"
    },
    "OFSS": {
      "status": "skipped",
      "reason": "ohlcv fetch failed"
    },
    "OIL": {
      "status": "skipped",
      "reason": "ohlcv fetch failed"
    },
    "ONGC": {
      "status": "skipped",
      "reason": "ohlcv fetch failed"
    },
    "PARAS": {
      "status": "skipped",
      "reason": "ohlcv fetch failed"
    },
    "PERSISTENT": {
      "status": "skipped",
      "reason": "ohlcv fetch failed"
    },
    "PETRONET": {
      "status": "skipped",
      "reason": "ohlcv fetch failed"
    },
    "PFC": {
      "status": "skipped",
      "reason": "ohlcv fetch failed"
    },
    "PGEL": {
      "status": "skipped",
      "reason": "ohlcv fetch failed"
    },
    "PHOENIXLTD": {
      "status": "skipped",
      "reason": "ohlcv fetch failed"
    },
    "PIDILITIND": {
      "status": "skipped",
      "reason": "ohlcv fetch failed"
    },
    "PIIND": {
      "status": "skipped",
      "reason": "ohlcv fetch failed"
    },
    "PNB": {
      "status": "skipped",
      "reason": "ohlcv fetch failed"
    },
    "PNCINFRA": {
      "status": "skipped",
      "reason": "ohlcv fetch failed"
    },
    "POWERGRID": {
      "status": "skipped",
      "reason": "ohlcv fetch failed"
    },
    "PRESTIGE": {
      "status": "skipped",
      "reason": "ohlcv fetch failed"
    },
    "RAILTEL": {
      "status": "skipped",
      "reason": "ohlcv fetch failed"
    },
    "RAMCOCEM": {
      "status": "skipped",
      "reason": "ohlcv fetch failed"
    },
    "RCF": {
      "status": "skipped",
      "reason": "ohlcv fetch failed"
    },
    "RCOM": {
      "status": "skipped",
      "reason": "no symboltoken found"
    },
    "RECLTD": {
      "status": "skipped",
      "reason": "ohlcv fetch failed"
    },
    "RELIANCE": {
      "status": "skipped",
      "reason": "ohlcv fetch failed"
    },
    "RTNPOWER": {
      "status": "skipped",
      "reason": "ohlcv fetch failed"
    },
    "RVNL": {
      "status": "skipped",
      "reason": "ohlcv fetch failed"
    },
    "SAIL": {
      "status": "skipped",
      "reason": "ohlcv fetch failed"
    },
    "SBIN": {
      "status": "skipped",
      "reason": "ohlcv fetch failed"
    },
    "SCTL": {
      "status": "skipped",
      "reason": "no symboltoken found"
    },
    "SENCO": {
      "status": "skipped",
      "reason": "ohlcv fetch failed"
    },
    "SHREECEM": {
      "status": "skipped",
      "reason": "ohlcv fetch failed"
    },
    "SHRIRAMFIN": {
      "status": "skipped",
      "reason": "ohlcv fetch failed"
    },
    "SJVN": {
      "status": "skipped",
      "reason": "ohlcv fetch failed"
    },
    "SONACOMS": {
      "status": "skipped",
      "reason": "ohlcv fetch failed"
    },
    "SPICEJET": {
      "status": "skipped",
      "reason": "no symboltoken found"
    },
    "SRF": {
      "status": "skipped",
      "reason": "ohlcv fetch failed"
    },
    "SUNPHARMA": {
      "status": "skipped",
      "reason": "ohlcv fetch failed"
    },
    "SUZLON": {
      "status": "skipped",
      "reason": "ohlcv fetch failed"
    },
    "SYMBIOX": {
      "status": "skipped",
      "reason": "no symboltoken found"
    },
    "SYRMA": {
      "status": "skipped",
      "reason": "ohlcv fetch failed"
    },
    "TATACHEM": {
      "status": "skipped",
      "reason": "ohlcv fetch failed"
    },
    "TATACONSUM": {
      "status": "skipped",
      "reason": "ohlcv fetch failed"
    },
    "TATAPOWER": {
      "status": "skipped",
      "reason": "ohlcv fetch failed"
    },
    "TATASTEEL": {
      "status": "skipped",
      "reason": "ohlcv fetch failed"
    },
    "TCI": {
      "status": "skipped",
      "reason": "ohlcv fetch failed"
    },
    "TCS": {
      "status": "skipped",
      "reason": "ohlcv fetch failed"
    },
    "TECHM": {
      "status": "skipped",
      "reason": "ohlcv fetch failed"
    },
    "TEXRAIL": {
      "status": "skipped",
      "reason": "ohlcv fetch failed"
    },
    "TITAGARH": {
      "status": "skipped",
      "reason": "ohlcv fetch failed"
    },
    "TITAN": {
      "status": "skipped",
      "reason": "ohlcv fetch failed"
    },
    "TMPV": {
      "status": "skipped",
      "reason": "ohlcv fetch failed"
    },
    "TORNTPHARM": {
      "status": "skipped",
      "reason": "ohlcv fetch failed"
    },
    "TORNTPOWER": {
      "status": "skipped",
      "reason": "ohlcv fetch failed"
    },
    "TVSMOTOR": {
      "status": "skipped",
      "reason": "ohlcv fetch failed"
    },
    "UJJIVANSFB": {
      "status": "skipped",
      "reason": "ohlcv fetch failed"
    },
    "ULTRACEMCO": {
      "status": "skipped",
      "reason": "ohlcv fetch failed"
    },
    "UNOMINDA": {
      "status": "skipped",
      "reason": "ohlcv fetch failed"
    },
    "UPL": {
      "status": "skipped",
      "reason": "ohlcv fetch failed"
    },
    "VBL": {
      "status": "skipped",
      "reason": "ohlcv fetch failed"
    },
    "VEDL": {
      "status": "skipped",
      "reason": "ohlcv fetch failed"
    },
    "WIPRO": {
      "status": "skipped",
      "reason": "ohlcv fetch failed"
    },
    "YESBANK": {
      "status": "skipped",
      "reason": "ohlcv fetch failed"
    },
    "ZYDUSLIFE": {
      "status": "skipped",
      "reason": "ohlcv fetch failed"
    }
  },
  "summary": {
    "total": 184,
    "ok": 39,
    "skipped": 145
  }
}