{
  "symbol": "LTTS",
  "name": "L&T Technology Services",
  "sector": "IT",
  "indicators": {
    "date": "2026-07-08",
    "close": 3141.1,
    "prev_close": 3221.3,
    "change_pct": -2.489678080278157,
    "ema20": 3255.8443733421186,
    "ema50": 3359.6492840111246,
    "ema200": 3712.242091442836,
    "rsi14": 41.11723184120083,
    "macd": -72.16501148723728,
    "macd_signal": -66.73134192883902,
    "atr14": 117.05494408702206,
    "adx14": 21.75045508799023,
    "adx_pos": 18.241694601884518,
    "adx_neg": 27.953996684594834,
    "bb_high": 3506.6470867917906,
    "bb_low": 3047.66291320821,
    "bb_mid": 3277.155,
    "vwap20": 3242.2786372387204
  },
  "flags": {
    "flags": {
      "price_above_ema20": false,
      "ema20_above_ema50": false,
      "ema50_above_ema200": false,
      "rsi_above_50": false,
      "macd_bullish": false,
      "adx_trending_up": false,
      "price_above_vwap20": false,
      "price_above_bb_mid": false
    },
    "flags_detail": {
      "price_above_ema20": "Close 3,141.10 vs EMA20 3,255.84",
      "ema20_above_ema50": "EMA20 3,255.84 vs EMA50 3,359.65",
      "ema50_above_ema200": "EMA50 3,359.65 vs EMA200 3,712.24",
      "rsi_above_50": "RSI(14) 41.12 vs 50",
      "macd_bullish": "MACD -72.17 vs signal -66.73",
      "adx_trending_up": "ADX(14) 21.75 vs 20, +DI 18.24 vs -DI 27.95",
      "price_above_vwap20": "Close 3,141.10 vs 20d VWAP 3,242.28",
      "price_above_bb_mid": "Close 3,141.10 vs BB mid 3,277.16"
    },
    "flags_on": [],
    "flag_count": 0,
    "flag_total": 8
  },
  "fundamentals": null,
  "shareholding": null,
  "updated_at": "2026-07-08T18:59:47.064886+00:00"
}