{
  "symbol": "TCI",
  "name": "Transport Corporation of India",
  "sector": "Logistics",
  "indicators": {
    "date": "2026-07-09",
    "close": 939.3,
    "prev_close": 931.45,
    "change_pct": 0.8427720221160457,
    "ema20": 935.3549595710577,
    "ema50": 940.0249767962304,
    "ema200": 1009.741994330358,
    "rsi14": 51.470039554209116,
    "macd": 1.0512922333862207,
    "macd_signal": 0.7028364504126202,
    "atr14": 23.989296885952363,
    "adx14": 16.948511266412346,
    "adx_pos": 17.658875621295792,
    "adx_neg": 8.81280923806389,
    "bb_high": 952.4330198901006,
    "bb_low": 919.0119801098996,
    "bb_mid": 935.7225000000001,
    "vwap20": 939.0169773857499
  },
  "flags": {
    "flags": {
      "price_above_ema20": true,
      "ema20_above_ema50": false,
      "ema50_above_ema200": false,
      "rsi_above_50": true,
      "macd_bullish": true,
      "adx_trending_up": false,
      "price_above_vwap20": true,
      "price_above_bb_mid": true
    },
    "flags_detail": {
      "price_above_ema20": "Close 939.30 vs EMA20 935.35",
      "ema20_above_ema50": "EMA20 935.35 vs EMA50 940.02",
      "ema50_above_ema200": "EMA50 940.02 vs EMA200 1,009.74",
      "rsi_above_50": "RSI(14) 51.47 vs 50",
      "macd_bullish": "MACD 1.05 vs signal 0.70",
      "adx_trending_up": "ADX(14) 16.95 vs 20, +DI 17.66 vs -DI 8.81",
      "price_above_vwap20": "Close 939.30 vs 20d VWAP 939.02",
      "price_above_bb_mid": "Close 939.30 vs BB mid 935.72"
    },
    "flags_on": [
      "price_above_ema20",
      "rsi_above_50",
      "macd_bullish",
      "price_above_vwap20",
      "price_above_bb_mid"
    ],
    "flag_count": 5,
    "flag_total": 8
  },
  "fundamentals": null,
  "shareholding": null,
  "updated_at": "2026-07-09T04:49:20.426050+00:00"
}