{
  "symbol": "YESBANK",
  "name": "Yes Bank",
  "sector": "Banking",
  "indicators": {
    "date": "2026-07-09",
    "close": 23.65,
    "prev_close": 23.42,
    "change_pct": 0.9820666097352555,
    "ema20": 24.014765846162334,
    "ema50": 23.072619736744695,
    "ema200": 21.510146788576577,
    "rsi14": 48.33241340081405,
    "macd": 0.2746056498696312,
    "macd_signal": 0.508418471799933,
    "atr14": 0.628611633136659,
    "adx14": 20.46544997932475,
    "adx_pos": 19.926202615500117,
    "adx_neg": 23.346674450318027,
    "bb_high": 25.910881836454024,
    "bb_low": 22.695118163545985,
    "bb_mid": 24.303000000000004,
    "vwap20": 24.513141862750675
  },
  "flags": {
    "flags": {
      "price_above_ema20": false,
      "ema20_above_ema50": true,
      "ema50_above_ema200": true,
      "rsi_above_50": false,
      "macd_bullish": false,
      "adx_trending_up": false,
      "price_above_vwap20": false,
      "price_above_bb_mid": false
    },
    "flags_detail": {
      "price_above_ema20": "Close 23.65 vs EMA20 24.01",
      "ema20_above_ema50": "EMA20 24.01 vs EMA50 23.07",
      "ema50_above_ema200": "EMA50 23.07 vs EMA200 21.51",
      "rsi_above_50": "RSI(14) 48.33 vs 50",
      "macd_bullish": "MACD 0.27 vs signal 0.51",
      "adx_trending_up": "ADX(14) 20.47 vs 20, +DI 19.93 vs -DI 23.35",
      "price_above_vwap20": "Close 23.65 vs 20d VWAP 24.51",
      "price_above_bb_mid": "Close 23.65 vs BB mid 24.30"
    },
    "flags_on": [
      "ema20_above_ema50",
      "ema50_above_ema200"
    ],
    "flag_count": 2,
    "flag_total": 8
  },
  "fundamentals": null,
  "shareholding": null,
  "updated_at": "2026-07-09T04:49:36.956828+00:00"
}